dately/__envutils.py
dately/__init__.py
dately/__os_config.py
dately/__user_agents_config.py
dately/_api.py
dately/_connect.py
dately/_datetime_scan.py
dately/_holiday.py
dately/_log.py
dately/_mskutils.py
dately/_proxy.py
dately/_sysutils.py
dately/_temporal_scan.py
dately/_timeutils.py
dately/_timezone.py
dately/_utils.py
dately/_version.py
dately/_webutils.py
dately/core.py
dately/dt_nlp/__init__.py
dately/dt_nlp/arithmetic.py
dately/dt_nlp/quantified_time.py
dately/dt_nlp/relative_time.py
dately/dt_nlp/temporal_preprocessing.py
dately/dt_nlp/lexical_validation/__init__.py
dately/dt_nlp/lexical_validation/vocabulary_checks.py
dately/dt_nlp/semantic_validation/__init__.py
dately/dt_nlp/semantic_validation/unit_bounds.py
dately/dt_nlp/string_similarity/__init__.py
dately/dt_nlp/string_similarity/spell_correction.py
dately/dt_nlp/syntactic_validation/__init__.py
dately/dt_nlp/syntactic_validation/structure_validator.py
dately/dt_nlp/syntactic_validation/temporal_structure_rules.py
dately/dt_nlp/temporal_core/__init__.py
dately/dt_nlp/temporal_core/temporal_units.py
dately/files/__init__.py
dately/files/country_variants.json
dately/files/holiday.json
dately/files/os_versions.json
dately/files/timezone_data.json
dately/files/user_agents.json
dately/mold/__init__.py
dately/mold/include/clean_str.h
dately/mold/include/iso8601T.h
dately/mold/include/iso8601Z.h
dately/mold/include/root_dir_search.h
dately/mold/include/time_zones.h
dately/mold/pyd/Compiled.cp38-win_amd64.pyd
dately/mold/pyd/__init__.py
dately/mold/pyd/clean_str.cp38-win_amd64.pyd
dately/mold/pyd/time_zones.cp38-win_amd64.pyd
dately/mold/pyd/cdatetime/UniversalDateFormatter.cp38-win_amd64.pyd
dately/mold/pyd/cdatetime/__init__.py
dately/mold/pyd/cdatetime/iso8601T.cp38-win_amd64.pyd
dately/mold/pyd/cdatetime/iso8601Z.cp38-win_amd64.pyd
dately/mold/pyd/cdatetime/whichformat.cp38-win_amd64.pyd
dately/mold/pyx/Compiled.pyx
dately/mold/pyx/UniversalDateFormatter.pyx
dately/mold/pyx/clean_str.pyx
dately-3.2.4.dist-info/METADATA
dately-3.2.4.dist-info/WHEEL
dately-3.2.4.dist-info/top_level.txt
dately-3.2.4.dist-info/RECORD
