Metadata-Version: 2.1
Name: dately
Version: 3.2.4
Summary: A comprehensive Python library for advanced date and time manipulation.
Home-page: https://github.com/cedricmoorejr/dately/tree/v3.2.4
Author: Cedric Moore Jr.
Author-email: cedricmoorejunior5@gmail.com
License: MIT
Project-URL: Source Code, https://github.com/cedricmoorejr/dately/releases/tag/v3.2.4
Classifier: Programming Language :: Python :: 3
Classifier: License :: OSI Approved :: MIT License
Classifier: Operating System :: Microsoft :: Windows
Classifier: Development Status :: 5 - Production/Stable
Classifier: Intended Audience :: Developers
Classifier: Natural Language :: English
Classifier: Programming Language :: Python :: 3.8
Classifier: Programming Language :: Python :: 3.9
Classifier: Programming Language :: Python :: 3.10
Requires-Python: >=3.8
Requires-Dist: numpy
Requires-Dist: pandas
Requires-Dist: pytz
Requires-Dist: requests
Requires-Dist: requests-cache
Requires-Dist: numbr
Requires-Dist: importlib-resources ; python_version < "3.9"
